serpent_cli/__init__.py
serpent_cli/__main__.py
serpent_cli/templates.lst
serpent_cli-0.0.2.dist-info/LICENSE
serpent_cli-0.0.2.dist-info/METADATA
serpent_cli-0.0.2.dist-info/WHEEL
serpent_cli-0.0.2.dist-info/entry_points.txt
serpent_cli-0.0.2.dist-info/top_level.txt
serpent_cli-0.0.2.dist-info/RECORD
