Metadata-Version: 2.1
Name: serpent-cli
Version: 0.0.2
Summary: A CLI-based Python project template tool
Author-email: Carl Furtado <carlzfurtado@gmail.com>
License: The MIT License (MIT)
Project-URL: Home, https://github.com/User0332/serpent
Classifier: License :: OSI Approved :: MIT License
License-File: LICENSE
Requires-Dist: virtualenv
Requires-Dist: flit
Requires-Dist: tomli
Requires-Dist: tomli-w
